ldc/__init__.py
ldc/data_preprocessing.py
ldc/liverDiseaseTools.py
ldc/model_training.py
liver_disease_classifier-0.1.0.dist-info/LICENSE
liver_disease_classifier-0.1.0.dist-info/METADATA
liver_disease_classifier-0.1.0.dist-info/WHEEL
liver_disease_classifier-0.1.0.dist-info/top_level.txt
liver_disease_classifier-0.1.0.dist-info/RECORD
